baycomp/__init__.py
baycomp/hierarchical-t-test.stan
baycomp/multiple.py
baycomp/single.py
baycomp/utils.py
tests/__init__.py
tests/test_multiple.py
tests/test_single.py
tests/test_utils.py
tests/utils.py
baycomp-1.0.2.dist-info/LICENSE
baycomp-1.0.2.dist-info/METADATA
baycomp-1.0.2.dist-info/WHEEL
baycomp-1.0.2.dist-info/top_level.txt
baycomp-1.0.2.dist-info/RECORD
