Metadata-Version: 2.1
Name: baycomp
Version: 1.0.2
Summary: Bayesian tests for comparison of classifiers
Home-page: https://github.com/janezd/baycomp.git
Author: J. Demsar, A. Benavoli, G. Corani
Author-email: janez.demsar@fri.uni-lj.si
License: UNKNOWN
Platform: UNKNOWN
Classifier: Development Status :: 5 - Production/Stable
Classifier: Intended Audience :: Science/Research
Classifier: Topic :: Scientific/Engineering :: Artificial Intelligence
Classifier: License :: OSI Approved :: MIT License
Classifier: Programming Language :: Python :: 3
Requires-Python: >=3
